controlnet_aux/__init__.py
controlnet_aux/processor.py
controlnet_aux/util.py
controlnet_aux/anyline/__init__.py
controlnet_aux/canny/__init__.py
controlnet_aux/dwpose/__init__.py
controlnet_aux/dwpose/util.py
controlnet_aux/dwpose/wholebody.py
controlnet_aux/dwpose/dwpose_config/__init__.py
controlnet_aux/dwpose/dwpose_config/dwpose-l_384x288.py
controlnet_aux/dwpose/yolox_config/__init__.py
controlnet_aux/dwpose/yolox_config/yolox_l_8xb8-300e_coco.py
controlnet_aux/hed/__init__.py
controlnet_aux/leres/__init__.py
controlnet_aux/leres/leres/Resnet.py
controlnet_aux/leres/leres/Resnext_torch.py
controlnet_aux/leres/leres/__init__.py
controlnet_aux/leres/leres/depthmap.py
controlnet_aux/leres/leres/multi_depth_model_woauxi.py
controlnet_aux/leres/leres/net_tools.py
controlnet_aux/leres/leres/network_auxi.py
controlnet_aux/leres/pix2pix/__init__.py
controlnet_aux/leres/pix2pix/models/__init__.py
controlnet_aux/leres/pix2pix/models/base_model.py
controlnet_aux/leres/pix2pix/models/base_model_hg.py
controlnet_aux/leres/pix2pix/models/networks.py
controlnet_aux/leres/pix2pix/models/pix2pix4depth_model.py
controlnet_aux/leres/pix2pix/options/__init__.py
controlnet_aux/leres/pix2pix/options/base_options.py
controlnet_aux/leres/pix2pix/options/test_options.py
controlnet_aux/leres/pix2pix/util/__init__.py
controlnet_aux/leres/pix2pix/util/util.py
controlnet_aux/lineart/__init__.py
controlnet_aux/lineart_anime/__init__.py
controlnet_aux/lineart_standard/__init__.py
controlnet_aux/mediapipe_face/__init__.py
controlnet_aux/mediapipe_face/mediapipe_face_common.py
controlnet_aux/midas/__init__.py
controlnet_aux/midas/api.py
controlnet_aux/midas/utils.py
controlnet_aux/midas/midas/__init__.py
controlnet_aux/midas/midas/base_model.py
controlnet_aux/midas/midas/blocks.py
controlnet_aux/midas/midas/dpt_depth.py
controlnet_aux/midas/midas/midas_net.py
controlnet_aux/midas/midas/midas_net_custom.py
controlnet_aux/midas/midas/transforms.py
controlnet_aux/midas/midas/vit.py
controlnet_aux_openpose_fix-0.0.10.dist-info/licenses/LICENSE.txt
controlnet_aux_openpose_fix-0.0.10.dist-info/METADATA
controlnet_aux_openpose_fix-0.0.10.dist-info/WHEEL
controlnet_aux_openpose_fix-0.0.10.dist-info/top_level.txt
controlnet_aux_openpose_fix-0.0.10.dist-info/RECORD
