Metadata-Version: 2.4
Name: controlnet_aux_openpose_fix
Version: 0.0.10
Summary: Auxillary models for controlnet
Home-page: https://github.com/patrickvonplaten/controlnet_aux
Author: The HuggingFace team
Author-email: patrick@huggingface.co
License: Apache
Keywords: deep learning
Classifier: Development Status :: 5 - Production/Stable
Classifier: Intended Audience :: Developers
Classifier: Intended Audience :: Education
Classifier: Intended Audience :: Science/Research
Classifier: License :: OSI Approved :: Apache Software License
Classifier: Operating System :: OS Independent
Classifier: Programming Language :: Python :: 3
Classifier: Programming Language :: Python :: 3.7
Classifier: Programming Language :: Python :: 3.8
Classifier: Programming Language :: Python :: 3.9
Classifier: Topic :: Scientific/Engineering :: Artificial Intelligence
Requires-Python: >=3.7.0
License-File: LICENSE.txt
Requires-Dist: torch
Requires-Dist: importlib_metadata
Requires-Dist: huggingface_hub
Requires-Dist: scipy
Requires-Dist: opencv-python-headless
Requires-Dist: filelock
Requires-Dist: numpy
Requires-Dist: Pillow
Requires-Dist: einops
Requires-Dist: torchvision
Requires-Dist: timm
Requires-Dist: scikit-image
Dynamic: author
Dynamic: author-email
Dynamic: classifier
Dynamic: description
Dynamic: description-content-type
Dynamic: home-page
Dynamic: keywords
Dynamic: license
Dynamic: license-file
Dynamic: requires-dist
Dynamic: requires-python
Dynamic: summary
